AUTHORS.rst
CONTRIBUTING.rst
HISTORY.rst
LICENSE
MANIFEST.in
README.rst
setup.cfg
setup.py
crispy_templates/__init__.py
crispy_templates/apps.py
crispy_templates/models.py
crispy_templates/urls.py
crispy_templates/views.py
crispy_templates.egg-info/PKG-INFO
crispy_templates.egg-info/SOURCES.txt
crispy_templates.egg-info/dependency_links.txt
crispy_templates.egg-info/not-zip-safe
crispy_templates.egg-info/top_level.txt
crispy_templates/static/css/crispy_templates.css
crispy_templates/static/js/crispy_templates.js
crispy_templates/templates/crispy_templates/layout/radio_btn_group_select.html