Metadata-Version: 1.1
Name: crispy-templates
Version: 0.1.0
Summary: A collection of useful templates for customizing crispy forms layouts.
Home-page: https://github.com/audiolion/crispy-templates
Author: Ryan Castner
Author-email: castner.rr@gmail.com
License: MIT
Keywords: crispy-templates
Platform: UNKNOWN
Classifier: Development Status :: 3 - Alpha
Classifier: Framework :: Django
Classifier: Framework :: Django :: 1.8
Classifier: Framework :: Django :: 1.9
Classifier: Framework :: Django :: 1.10
Classifier: Intended Audience :: Developers
Classifier: License :: OSI Approved :: MIT License
Classifier: Natural Language :: English
Classifier: Programming Language :: Python :: 2
Classifier: Programming Language :: Python :: 2.7
Classifier: Programming Language :: Python :: 3
Classifier: Programming Language :: Python :: 3.2
Classifier: Programming Language :: Python :: 3.3
Classifier: Programming Language :: Python :: 3.4
Classifier: Programming Language :: Python :: 3.5
